CHANGELOG.md
LICENSE
pylintrc
pyinstaller_versionfile/__init__.py
pyinstaller_versionfile/__main__.py
pyinstaller_versionfile/exceptions.py
pyinstaller_versionfile/metadata.py
pyinstaller_versionfile/py.typed
pyinstaller_versionfile/version_file_template.txt
pyinstaller_versionfile/writer.py
tox.ini
pyinstaller_versionfile-3.0.1.dist-info/LICENSE
pyinstaller_versionfile-3.0.1.dist-info/METADATA
pyinstaller_versionfile-3.0.1.dist-info/WHEEL
pyinstaller_versionfile-3.0.1.dist-info/entry_points.txt
pyinstaller_versionfile-3.0.1.dist-info/RECORD
