Metadata-Version: 2.1
Name: pyinstaller_versionfile
Version: 3.0.1
Summary: Create a windows version-file from metadata stored in a simple self-written YAML file or obtained from an installed distribution.
Home-page: https://github.com/DudeNr33/pyinstaller-versionfile
License: MIT
Author: Andreas Finkler
Requires-Python: >=3.9,<4.0
Classifier: Environment :: Console
Classifier: License :: OSI Approved :: MIT License
Classifier: Operating System :: Microsoft :: Windows
Classifier: Programming Language :: Python :: 3
Classifier: Programming Language :: Python :: 3.9
Classifier: Programming Language :: Python :: 3.10
Classifier: Programming Language :: Python :: 3.11
Classifier: Programming Language :: Python :: 3.12
Classifier: Topic :: Software Development
Classifier: Topic :: Software Development :: Build Tools
Requires-Dist: Jinja2
Requires-Dist: PyYAML
Requires-Dist: packaging
Project-URL: Repository, https://github.com/DudeNr33/pyinstaller-versionfile
